tisa/__init__.py
tisa-0.1.0a1.dist-info/LICENSE
tisa-0.1.0a1.dist-info/METADATA
tisa-0.1.0a1.dist-info/WHEEL
tisa-0.1.0a1.dist-info/top_level.txt
tisa-0.1.0a1.dist-info/RECORD
